Metadata-Version: 2.1
Name: auto-fastapi
Version: 0.1.1
Summary: A pythonic functional way to construct FastAPI applications be declaring endpoints in separation of their functional definition, enabeling to separate, replicate, and reuse functions in different APIs at the same time, and also run multiple of them.
Home-page: https://github.com/Shahaf-F-S/auto-fastapi
Author: Shahaf Frank-Shapir
Author-email: shahaffrs@gmail.com
License: MIT
Classifier: Intended Audience :: Developers
Classifier: License :: OSI Approved :: MIT License
Classifier: Programming Language :: Python
Classifier: Programming Language :: Python :: 3
Classifier: Programming Language :: Python :: 3.8
Classifier: Programming Language :: Python :: 3.9
Classifier: Programming Language :: Python :: 3.10
Classifier: Programming Language :: Python :: 3.11
Classifier: Operating System :: OS Independent
Requires-Dist: fastapi
Requires-Dist: uvicorn
Requires-Dist: dataplace
Provides-Extra: dev
